[
  {
    "id": "93142586",
    "companyName": "Liberty Mutual Insurance Group",
    "contactEmail": "Jream@libertymutual",
    "companyPlan": "free"
  },
  {
    "id": "89745734",
    "companyName": "Marathon Petroleum",
    "contactEmail": "Isabela@marathonpetroco",
    "companyPlan": "free"
  },
  {
    "id": "04995253",
    "companyName": "Archer Daniels Midland",
    "contactEmail": "Love@admupdates",
    "companyPlan": "paying"
  },
  {
    "id": "46875836",
    "companyName": "Goldman Sachs Group",
    "contactEmail": "Arlet@goldmansachs",
    "companyPlan": "free"
  },
  {
    "id": "19586061",
    "companyName": "State Farm Insurance Cos.",
    "contactEmail": "Isabela@statefarm",
    "companyPlan": "paying"
  },
  {
    "id": "49431785",
    "companyName": "Exxon Mobil",
    "contactEmail": "Zhuri@exxonmobil",
    "companyPlan": "paying"
  },
  {
    "id": "33086175",
    "companyName": "Facebook",
    "contactEmail": "Neriah@facebook",
    "companyPlan": "paying"
  },
  {
    "id": "62404534",
    "companyName": "Cisco Systems",
    "contactEmail": "Amayah@cisco",
    "companyPlan": "free"
  },
  {
    "id": "32580709",
    "companyName": "Anthem",
    "contactEmail": "Isabela@antheminc",
    "companyPlan": "free"
  },
  {
    "id": "66253295",
    "companyName": "Phillips",
    "contactEmail": "Amayah@phillips66co",
    "companyPlan": "paying"
  },
  {
    "id": "19692121",
    "companyName": "UnitedHealth Group",
    "contactEmail": "Wrenley@unitedhealthgrp",
    "companyPlan": "paying"
  },
  {
    "id": "18010157",
    "companyName": "AIG",
    "contactEmail": "Amayah@aiginsurance",
    "companyPlan": "paying"
  },
  {
    "id": "57814383",
    "companyName": "Wells Fargo",
    "contactEmail": "Alora@wellsfargo",
    "companyPlan": "free"
  },
  {
    "id": "04366510",
    "companyName": "Fannie Mae",
    "contactEmail": "Adalee@fanniemae",
    "companyPlan": "free"
  },
  {
    "id": "89267231",
    "companyName": "Home Depot",
    "contactEmail": "Jream@homedepot",
    "companyPlan": "free"
  },
  {
    "id": "28242471",
    "companyName": "Morgan Stanley",
    "contactEmail": "Arleth@morganstanley",
    "companyPlan": "paying"
  },
  {
    "id": "83148706",
    "companyName": "Berkshire Hathaway",
    "contactEmail": "Zhuri@bhhsrealestate",
    "companyPlan": "free"
  },
  {
    "id": "67519138",
    "companyName": "Comcast",
    "contactEmail": "Winona@comcast",
    "companyPlan": "paying"
  },
  {
    "id": "26469264",
    "companyName": "New York Life Insurance",
    "contactEmail": "Cielo@newyorklife",
    "companyPlan": "free"
  },
  {
    "id": "43332557",
    "companyName": "Lowe's",
    "contactEmail": "Cielo@lowes",
    "companyPlan": "paying"
  },
  {
    "id": "71737826",
    "companyName": "Delta Air Lines",
    "contactEmail": "Zhuri@delta",
    "companyPlan": "free"
  },
  {
    "id": "97677994",
    "companyName": "DowDuPont",
    "contactEmail": "Neriah@dowchemical",
    "companyPlan": "free"
  },
  {
    "id": "52025996",
    "companyName": "Aetna",
    "contactEmail": "Amayah@aetna",
    "companyPlan": "paying"
  },
  {
    "id": "52927145",
    "companyName": "Walmart",
    "contactEmail": "Georgina@walmart",
    "companyPlan": "paying"
  },
  {
    "id": "75096759",
    "companyName": "Ford Motor",
    "contactEmail": "Amayah@ford",
    "companyPlan": "free"
  },
  {
    "id": "86797788",
    "companyName": "Express Scripts Holding",
    "contactEmail": "Jream@expressscripts",
    "companyPlan": "paying"
  },
  {
    "id": "48608879",
    "companyName": "AmerisourceBergen",
    "contactEmail": "Sol@healthcare_abc",
    "companyPlan": "paying"
  },
  {
    "id": "21439174",
    "companyName": "CVS Health",
    "contactEmail": "Alora@cvspharmacy",
    "companyPlan": "paying"
  },
  {
    "id": "19002050",
    "companyName": "JPMorgan Chase",
    "contactEmail": "Sol@jpmorgan",
    "companyPlan": "free"
  },
  {
    "id": "08703161",
    "companyName": "Valero Energy",
    "contactEmail": "Amiri@valeroenergy",
    "companyPlan": "paying"
  }
]